dvc_cc_agent/__init__.py
dvc_cc_agent/__main__.py
dvc_cc_agent/bcolors.py
dvc_cc_agent/copy_output_files.py
dvc_cc_agent/main.py
dvc_cc_agent/start_dvc_repro.sh
dvc_cc_agent/version.py
dvc_cc_agent-0.10.2.dist-info/entry_points.txt
dvc_cc_agent-0.10.2.dist-info/WHEEL
dvc_cc_agent-0.10.2.dist-info/METADATA
dvc_cc_agent-0.10.2.dist-info/RECORD
